SDR33423312/__init__.py
SDR33423312/gyat.py
SDR3423312-0.0.1.dist-info/METADATA
SDR3423312-0.0.1.dist-info/WHEEL
SDR3423312-0.0.1.dist-info/top_level.txt
SDR3423312-0.0.1.dist-info/RECORD
