Metadata-Version: 2.1
Name: SDR3423312
Version: 0.0.1
Summary: calculate golden ratio
Home-page: 
Author: 
Author-email: 
License: MIT
Keywords: golden_ratio,golden
Classifier: Development Status :: 1 - Planning
